<GuidebookXML>
  <guide>
    <name>SQLSaturday #262 - Boston 2014</name>
    <startDate>3/29/2014 12:00:00 AM</startDate>
    <attendeeEstimate>300</attendeeEstimate>
    <timezone>(GMT-05:00) Indiana (East)</timezone>
    <description>SQLSaturday is a training event for SQL Server professionals and those wanting to learn about SQL Server. </description>
    <twitterHashtag>#sqlsat262</twitterHashtag>
    <venue>
      <name>Microsoft Conference Center, Kendall Square</name>
      <street>1 Cambridge Center</street>
      <city>Cambridge</city>
      <state>Massachusetts</state>
      <zipcode>02142</zipcode>
      <longitude>-71.0853014</longitude>
      <latitude>42.3629487</latitude>
    </venue>
  </guide>
  <sponsors>
    <sponsor>
      <importID>404</importID>
      <name>Atrion Networking Corporation</name>
      <label>Gold Sponsor</label>
      <url>http://www.atrion.net/Pages/default.aspx</url>
      <imageURL>https://www.atrion.net/PublishingImages/atrion_logo_secure.gif</imageURL>
      <imageHeight>60</imageHeight>
      <imageWidth>170</imageWidth>
    </sponsor>
    <sponsor>
      <importID>70</importID>
      <name>Tegile Systems</name>
      <label>Gold Sponsor</label>
      <url>http://www.tegile.com</url>
      <imageURL>https://www.pass.org/images/SQLSaturday/EventSponsors/Tegile_170x60.png</imageURL>
      <imageHeight>60</imageHeight>
      <imageWidth>170</imageWidth>
    </sponsor>
    <sponsor>
      <importID>1</importID>
      <name>Confio</name>
      <label>Gold Sponsor</label>
      <url>http://www.confio.com</url>
      <imageURL>https://www.pass.org/images/resized-confio_logo.png</imageURL>
      <imageHeight>60</imageHeight>
      <imageWidth>170</imageWidth>
    </sponsor>
    <sponsor>
      <importID>78</importID>
      <name>Cisco</name>
      <label>Gold Sponsor</label>
      <url>http://www.cisco.com/go/microsoft</url>
      <imageURL>https://i.imgur.com/kSHUsSB.jpg</imageURL>
      <imageHeight>60</imageHeight>
      <imageWidth>170</imageWidth>
    </sponsor>
    <sponsor>
      <importID>3</importID>
      <name>Idera</name>
      <label>Gold Sponsor</label>
      <url>http://www.idera.com/Content/Home.aspx</url>
      <imageURL>https://www.sqlsaturday.com/images/SQLSaturday/eventsponsors/IDERA170x60.png</imageURL>
      <imageHeight>60</imageHeight>
      <imageWidth>170</imageWidth>
    </sponsor>
    <sponsor>
      <importID>13</importID>
      <name>Quest Software</name>
      <label>Gold Sponsor</label>
      <url>https://www.quest.com/</url>
      <imageURL>https://www.sqlsaturday.com/images/sqlsaturday/eventsponsors/Quest_170x60.png</imageURL>
      <imageHeight>60</imageHeight>
      <imageWidth>170</imageWidth>
    </sponsor>
    <sponsor>
      <importID>23</importID>
      <name>Pragmatic Works</name>
      <label>Gold Sponsor</label>
      <url>http://www.pragmaticworks.com</url>
      <imageURL>https://sqlsaturdayfiles.blob.core.windows.net/973/EventSponsor_14499.png</imageURL>
      <imageHeight>60</imageHeight>
      <imageWidth>170</imageWidth>
    </sponsor>
    <sponsor>
      <importID>845</importID>
      <name>Microsoft Corporation (GAP)</name>
      <label>Gold Sponsor</label>
      <url>http://www.microsoft.com/en-us/server-cloud/products/sql-server/</url>
      <imageURL>https://geeks.ms/johnbulla/wp-content/uploads/sites/199/2016/04/Microsoft_logo_2012.svg_.png</imageURL>
      <imageHeight>60</imageHeight>
      <imageWidth>170</imageWidth>
    </sponsor>
    <sponsor>
      <importID>826</importID>
      <name>New England SQL User Group</name>
      <label>Silver Sponsor</label>
      <url>http://www.meetup.com/NESQLUG/</url>
      <imageURL>https://mikehillwig.com/sqlsat262/logo-2x.jpg</imageURL>
      <imageHeight>60</imageHeight>
      <imageWidth>170</imageWidth>
    </sponsor>
    <sponsor>
      <importID>58</importID>
      <name>Data Education</name>
      <label>Silver Sponsor</label>
      <url>http://dataeducation.com</url>
      <imageURL>
      </imageURL>
      <imageHeight>60</imageHeight>
      <imageWidth>170</imageWidth>
    </sponsor>
    <sponsor>
      <importID>59</importID>
      <name>Embarcadero</name>
      <label>Bronze Sponsor</label>
      <url>http://www.embarcadero.com</url>
      <imageURL>
      </imageURL>
      <imageHeight>60</imageHeight>
      <imageWidth>170</imageWidth>
    </sponsor>
    <sponsor>
      <importID>1184</importID>
      <name>Tek Systems</name>
      <label>Bronze Sponsor</label>
      <url>http://www.teksystems.com/</url>
      <imageURL>https://sqlsaturdayfiles.blob.core.windows.net/855/EventSponsor_13925.jpg</imageURL>
      <imageHeight>60</imageHeight>
      <imageWidth>170</imageWidth>
    </sponsor>
    <sponsor>
      <importID>857</importID>
      <name>mikehillwig.com</name>
      <label>Blog and Personal Sponsor</label>
      <url>http://www.mikehillwig.com</url>
      <imageURL>https://mikehillwig.com/wp-content/uploads/2013/07/sqlsat262.jpg</imageURL>
      <imageHeight>40</imageHeight>
      <imageWidth>100</imageWidth>
    </sponsor>
    <sponsor>
      <importID>85</importID>
      <name>Pyramid Analytics</name>
      <label>Platinum Sponsor</label>
      <url>http://www.PyramidAnalytics.com</url>
      <imageURL>http://pages.pyramidanalytics.com/rs/pyramidanalytics/images/logo.jpg</imageURL>
      <imageHeight>60</imageHeight>
      <imageWidth>170</imageWidth>
    </sponsor>
    <sponsor>
      <importID>7</importID>
      <name>SIOS Technology</name>
      <label>Platinum Sponsor</label>
      <url>http://us.sios.com/company/</url>
      <imageURL>https://sqlsaturdayfiles.blob.core.windows.net/956/EventSponsor_14655.jpg</imageURL>
      <imageHeight>60</imageHeight>
      <imageWidth>170</imageWidth>
    </sponsor>
  </sponsors>
  <speakers>
    <speaker>
      <importID>11258</importID>
      <name>Chris Bell</name>
      <label>
      </label>
      <description>Chris Bell offers a unique view of how we live and work with data, both now and as we head into the future. Having braved many roles, lifecycles, and battles in the IT world, he has honed his DBA (Database Administration or Do 'Bout Anything) skills in Information Systems and development, focusing on SQL Server. Currently, he serves as the lead DBA at The Motley Fool. You can keep up with Chris' thoughts and technical community activities at WaterOxConsulting.com.</description>
      <twitter>@cbelldba</twitter>
      <linkedin>http://www.linkedin.com/pub/christopher-bell/19/a08/93/</linkedin>
      <ContactURL>https://www.wateroxconsulting.com/</ContactURL>
      <imageURL>https://api.twitter.com/1/users/profile_image?screen_name=@cbelldba</imageURL>
      <imageHeight>48</imageHeight>
      <imageWidth>48</imageWidth>
    </speaker>
    <speaker>
      <importID>16205</importID>
      <name>Joseph D'Antoni</name>
      <label>
      </label>
      <description>Joseph D'Antoni is a Senior Consultant and Microsoft Data Platform MVP with over 20 years of experience working in both Fortune 500 and smaller firms. He is a Principal Consultant for Denny Cherry  Associates and lives in Malvern, PA. He is a frequent speaker at major tech events like Microsoft Ignite, PASS Summit, and Enterprise Data World. He blogs about all topics technology at joeydantoni.com. He believes that no single platform is the answer to all technology problems. Joseph holds a BS in Computer Information Systems from Louisiana Tech University and an MBA from North Carolina State University, and is the co-author of the Microsoft book "Introducing SQL Server 2016”.</description>
      <twitter>jdanton</twitter>
      <linkedin>http://www.linkedin.com/profile/view?id=3997984amp;trk=hb_tab_pro_top</linkedin>
      <ContactURL>http://joeydantoni.com</ContactURL>
      <imageURL>https://api.twitter.com/1/users/profile_image?screen_name=jdanton</imageURL>
      <imageHeight>48</imageHeight>
      <imageWidth>48</imageWidth>
    </speaker>
    <speaker>
      <importID>26709</importID>
      <name>Tim Radney</name>
      <label>
      </label>
      <description>Tim is a Data Platform MVP and has a whole collection of Microsoft and other industry certifications. His experience includes HA/DR, virtualization, SSIS, SSRS, and performance tuning, among everything else SQL Server-related.
Tim is very active and passionate in the SQL Community. He runs the Columbus GA SQL Users Group, has been a PASS Regional Mentor for a number of years, was named a PASS Outstanding Volunteer in 2012, and is a frequent speaker at user groups, SQL Saturdays and PASS Summits. Tim is one of the top ranked in karma on ask.sqlservercentral.com, answers questions as @tradney on Twitter, and blogs at http://timradney.com and SQLskills blog at http://www.SQLskills.com/blogs/tim.</description>
      <twitter>@tradney</twitter>
      <linkedin>http://linkedin.com/in/tradney</linkedin>
      <ContactURL>http://www.timradney.com</ContactURL>
      <imageURL>https://api.twitter.com/1/users/profile_image?screen_name=@tradney</imageURL>
      <imageHeight>48</imageHeight>
      <imageWidth>48</imageWidth>
    </speaker>
    <speaker>
      <importID>10149</importID>
      <name>Bradley Ball</name>
      <label>
      </label>
      <description>Bradley Ball is a Sr. Azure Engineer for Microsoft, and former Data Platform MVP. During his IT career Bradley has spent 8 years working as a Defense contractor for clients such as the U.S. Army and The Executive Office of the President of the United States, and the former Data Platform Practice Manager for Pragmatic Works Consulting.  He has presented at SQL Saturdays, SSUG's, SQL Rally, DevConnections, SQLBits, SQL Live 360, and the PASS Summit.  Bradley can be found blogging on http://www.SQLBalls.com</description>
      <twitter>@SQLBalls</twitter>
      <linkedin>https://www.linkedin.com/in/sqlballs</linkedin>
      <ContactURL>http://www.sqlballs.com</ContactURL>
      <imageURL>https://api.twitter.com/1/users/profile_image?screen_name=@SQLBalls</imageURL>
      <imageHeight>48</imageHeight>
      <imageWidth>48</imageWidth>
    </speaker>
    <speaker>
      <importID>11025</importID>
      <name>Bryan Cafferky</name>
      <label>
      </label>
      <description>Bryan Cafferky is a Big Data and AI consultant and creator of a popular Data and AI YouTube channel.   He was previously a Data Science Training Developer for Microsoft Worldwide Learning and a Microsoft Data and AI Enabler. He is a Microsoft 2017 Data Platform MVP and a 2016 Cloud and Data Center Management MVP. Bryan is the author of Master Azure Databricks Step by Step, available on Amazon. He leads The RI Microsoft BI User Group. He has been working with the SQL Server stack for decades and implemented projects in the banking, insurance, e-commerce, utility, and health care industries. He holds a bachelor of science in computer information systems and an MBA.</description>
      <twitter>
      </twitter>
      <linkedin>https://www.linkedin.com/pub/bryancafferky</linkedin>
      <ContactURL>https://www.youtube.com/user/Bryancutube256123</ContactURL>
      <imageURL>https://api.twitter.com/1/users/profile_image?screen_name=</imageURL>
      <imageHeight>48</imageHeight>
      <imageWidth>48</imageWidth>
    </speaker>
    <speaker>
      <importID>9511</importID>
      <name>Andy Leonard</name>
      <label>
      </label>
      <description>Andy Leonard is founder and Chief Data Engineer at Enterprise Data  Analytics, Microsoft Data Platform MVP, creator of the DILM (Data Integration Lifecycle Management) Suite, an SSIS trainer, consultant, developer, Business Intelligence Markup Language (Biml) developer and BimlHero, SQL Server database and data warehouse developer, community mentor, engineer, and farmer. He is a co-author of "The Biml Book and SQL Server Integration Services Design Patterns" and author of "Managing Geeks - A Journey of Leading by Doing", "Data Integration Lifecycle Management with SSIS", "Building Custom Tasks for SSIS", and the "Stairway to Integration Services". Andy blogs at andyleonard.blog where you can learn more on the About Andy page.</description>
      <twitter>AndyLeonard</twitter>
      <linkedin>http://www.linkedin.com/in/AndyLeonard</linkedin>
      <ContactURL>https://andyleonard.blog</ContactURL>
      <imageURL>https://api.twitter.com/1/users/profile_image?screen_name=AndyLeonard</imageURL>
      <imageHeight>48</imageHeight>
      <imageWidth>48</imageWidth>
    </speaker>
    <speaker>
      <importID>11024</importID>
      <name>Bryan Cafferky</name>
      <label>
      </label>
      <description>Bryan Cafferky is a Big Data and AI consultant and creator of a popular Data and AI YouTube channel.   He was previously a Data Science Training Developer for Microsoft Worldwide Learning and a Microsoft Data and AI Enabler. He is a Microsoft 2017 Data Platform MVP and a 2016 Cloud and Data Center Management MVP. Bryan is the author of Master Azure Databricks Step by Step, available on Amazon. He leads The RI Microsoft BI User Group. He has been working with the SQL Server stack for decades and implemented projects in the banking, insurance, e-commerce, utility, and health care industries. He holds a bachelor of science in computer information systems and an MBA.</description>
      <twitter>
      </twitter>
      <linkedin>https://www.linkedin.com/pub/bryancafferky</linkedin>
      <ContactURL>https://www.youtube.com/user/Bryancutube256123</ContactURL>
      <imageURL>https://api.twitter.com/1/users/profile_image?screen_name=</imageURL>
      <imageHeight>48</imageHeight>
      <imageWidth>48</imageWidth>
    </speaker>
    <speaker>
      <importID>27546</importID>
      <name>Varsham Papikian</name>
      <label>
      </label>
      <description>Varsham Papikian has 20+ years of experience working with databases and different Microsoft technologies.
 He works as a Principal Database Architect, Developer and DBA at Wolters Kluwer Financial Services. He speaks at different events like SQLSaturday or user group meetings. Varsham helped to start and then run 'Boston Business Intelligence' user group for some time. Previously he was also involved in running 'New England SQL Server' user group.</description>
      <twitter>https://twitter.com/SQLVAR</twitter>
      <linkedin>http://www.linkedin.com/in/varshampapikian</linkedin>
      <ContactURL>
      </ContactURL>
      <imageURL>https://api.twitter.com/1/users/profile_image?screen_name=https://twitter.com/SQLVAR</imageURL>
      <imageHeight>48</imageHeight>
      <imageWidth>48</imageWidth>
    </speaker>
    <speaker>
      <importID>23794</importID>
      <name>Mohammad Yusuf</name>
      <label>
      </label>
      <description>Mohammad “Saleem” Yusuf has more than 35 years of industry experience and is currently a full-time Professor at NHTI - Concord’s Community college. He teaches database design and computer programming courses.
Saleem earned his Bachelors’ degree from University of Lowell (UMass Lowell). He also has technical certificates from Northeastern University and Worcester Polytechnic Institute.
</description>
      <twitter>@syusuf</twitter>
      <linkedin>https://www.linkedin.com/in/saleemyusuf</linkedin>
      <ContactURL>
      </ContactURL>
      <imageURL>https://api.twitter.com/1/users/profile_image?screen_name=@syusuf</imageURL>
      <imageHeight>48</imageHeight>
      <imageWidth>48</imageWidth>
    </speaker>
    <speaker>
      <importID>10070</importID>
      <name>Ayad Shammout</name>
      <label>
      </label>
      <description>Ayad Shammout is a Database amp; BI Specialist and Microsoft MVP. He has more than 25 years deep experience in Database technologies and specializing in SQL Server, SharePoint, Windows OS. Shammout is working in OLTP design and development, Data Warehousing, Business Intelligence and Big Data, with extensive experience in data management and analysis. Ayad has been involved in many SQL Server Enterprise implementations for High-Availability, DR, Business Intelligence, Data Mining and Big Data.</description>
      <twitter>@aashammout</twitter>
      <linkedin>http://www.linkedin.com/in/ayadshammout/</linkedin>
      <ContactURL>http://ayadshammout.com/</ContactURL>
      <imageURL>https://api.twitter.com/1/users/profile_image?screen_name=@aashammout</imageURL>
      <imageHeight>48</imageHeight>
      <imageWidth>48</imageWidth>
    </speaker>
    <speaker>
      <importID>10670</importID>
      <name>Brandon Leach</name>
      <label>
      </label>
      <description>A Microsoft Data Platform MVP, Brandon manages the DB Operations team for financial company x. With a data estate of several petabytes, he puts a high focus on performance tuning and automation. He is a frequent speaker at events like conferences and user groups.</description>
      <twitter>SQLServerNerd</twitter>
      <linkedin>https://www.linkedin.com/in/sqlservernerd</linkedin>
      <ContactURL>
      </ContactURL>
      <imageURL>https://api.twitter.com/1/users/profile_image?screen_name=SQLServerNerd</imageURL>
      <imageHeight>48</imageHeight>
      <imageWidth>48</imageWidth>
    </speaker>
    <speaker>
      <importID>24658</importID>
      <name>Stacia Varga</name>
      <label>
      </label>
      <description>Stacia Varga is a Microsoft Data Platform MVP and SSAS Maestro with a Bachelor’s Degree in Social Sciences. A consultant, educator, author, and principal of Data Inspirations, her career spans more than 30 years, with a focus on improving business practices through technology.

Since 2000, Stacia has provided consulting and education services for Microsoft's Business Intelligence technologies. As Stacia Misner, she also authored several books covering the Microsoft BI stack.</description>
      <twitter>@_StaciaV_</twitter>
      <linkedin>http://www.linkedin.com/in/staciavarga</linkedin>
      <ContactURL>http://blog.datainspirations.com</ContactURL>
      <imageURL>https://api.twitter.com/1/users/profile_image?screen_name=@_StaciaV_</imageURL>
      <imageHeight>48</imageHeight>
      <imageWidth>48</imageWidth>
    </speaker>
    <speaker>
      <importID>13832</importID>
      <name>Edward Pollack</name>
      <label>
      </label>
      <description>Ed Pollack has over 20 years of experience in database and systems administration, which has developed his passion for performance optimization, database design, and making things go faster. He has spoken at many SQLSaturdays, 24 Hours of PASS, and PASS Summit. This led him to organize SQLSaturday Albany, which has become an annual event for New York’s Capital Region. Sharing these experiences with the community is a top priority, and encouraging everyone to take the leap into public speaking and engaging others, a passion.
In his free time, Ed enjoys video games, traveling, cooking exceptionally spicy foods, and hanging out with his amazing wife and sons.</description>
      <twitter>EdwardPollack</twitter>
      <linkedin>https://www.linkedin.com/profile/view?id=81593638</linkedin>
      <ContactURL>https://www.sqlshack.com/author/edward-pollack/</ContactURL>
      <imageURL>https://api.twitter.com/1/users/profile_image?screen_name=EdwardPollack</imageURL>
      <imageHeight>48</imageHeight>
      <imageWidth>48</imageWidth>
    </speaker>
    <speaker>
      <importID>26710</importID>
      <name>Tim Radney</name>
      <label>
      </label>
      <description>Tim is a Data Platform MVP and has a whole collection of Microsoft and other industry certifications. His experience includes HA/DR, virtualization, SSIS, SSRS, and performance tuning, among everything else SQL Server-related.
Tim is very active and passionate in the SQL Community. He runs the Columbus GA SQL Users Group, has been a PASS Regional Mentor for a number of years, was named a PASS Outstanding Volunteer in 2012, and is a frequent speaker at user groups, SQL Saturdays and PASS Summits. Tim is one of the top ranked in karma on ask.sqlservercentral.com, answers questions as @tradney on Twitter, and blogs at http://timradney.com and SQLskills blog at http://www.SQLskills.com/blogs/tim.</description>
      <twitter>@tradney</twitter>
      <linkedin>http://linkedin.com/in/tradney</linkedin>
      <ContactURL>http://www.timradney.com</ContactURL>
      <imageURL>https://api.twitter.com/1/users/profile_image?screen_name=@tradney</imageURL>
      <imageHeight>48</imageHeight>
      <imageWidth>48</imageWidth>
    </speaker>
    <speaker>
      <importID>21643</importID>
      <name>Paresh Motiwala</name>
      <label>
      </label>
      <description>Paresh Motiwala a Azure/Big Data enthusiast, Manager of Database Platform teams has led several large SQL implementations, migrations and upgrades. He has managed multi terabyte OLTP databases. He has also been a Sr. SQL DBA and a Solutions Architect in Fortune 100 companies.  He helps/organizes and speaks at many SQL Saturdays, Azure Bootcamp, Azure Datafests and User Groups(Boston BI UG, NESQL, PASS PD VG and PASS DBA VG).

He is certified in Big Data Analytics, FinTech, PMP, Public Speaking, Business Communications. He is a avid singer, cook, open networker, and stand-up comedian. 
He teaches public speaking, debating, interviewing and group discussion skills and mentors children around the globe via www.circlesofgrowth.com</description>
      <twitter>pareshmotiwala</twitter>
      <linkedin>http://www.linkedin.com/in/pareshmotiwala</linkedin>
      <ContactURL>https://pareshmotiwala.wordpress.com/wp-admin/post.php?post=2amp;action=editamp;message=6amp;postpost=v2</ContactURL>
      <imageURL>https://api.twitter.com/1/users/profile_image?screen_name=pareshmotiwala</imageURL>
      <imageHeight>48</imageHeight>
      <imageWidth>48</imageWidth>
    </speaker>
    <speaker>
      <importID>17044</importID>
      <name>John Miner</name>
      <label>
      </label>
      <description>John has over twenty years of IT experience including a Masters degree in Computer Science from the University of Rhode Island with concentrations in database technologies and programming languages. He also has Microsoft Certificates for Database Administration (MCDBA) and System Admistration (MCSA). John is currently a Senior SQL Server Developer / Administrator in charge of best practices by the IT team at Sensata Technologies. </description>
      <twitter>JohnMiner3</twitter>
      <linkedin>http://www.linkedin.com/pub/john-miner/a/85a/889</linkedin>
      <ContactURL>http://www.craftydba.com</ContactURL>
      <imageURL>https://api.twitter.com/1/users/profile_image?screen_name=JohnMiner3</imageURL>
      <imageHeight>48</imageHeight>
      <imageWidth>48</imageWidth>
    </speaker>
    <speaker>
      <importID>10591</importID>
      <name>Bob Pusateri</name>
      <label>
      </label>
      <description>Bob Pusateri is a Microsoft Certified Master, DBA, and systems architect with over 10 years of experience on SQL Server. His interests involve internals, performance optimization, and cloud technologies. He is an active member of two Chicago-area PASS Local Groups, a community speaker, and maintains a web presence through both Twitter (@SQLBob) and his blog (bobpusateri.com).</description>
      <twitter>@SQLBob</twitter>
      <linkedin>http://www.linkedin.com/in/bobpusateri</linkedin>
      <ContactURL>http://www.BobPusateri.com</ContactURL>
      <imageURL>https://api.twitter.com/1/users/profile_image?screen_name=@SQLBob</imageURL>
      <imageHeight>48</imageHeight>
      <imageWidth>48</imageWidth>
    </speaker>
    <speaker>
      <importID>14731</importID>
      <name>Grant Fritchey</name>
      <label>
      </label>
      <description>Grant Fritchey is a Data Platform MVP with over 20 years’ experience in IT, including time spent in support and development. He has worked with SQL Server since 6.0 back in 1995. He has also developed in VB, VB.NET, C#, and Java. Grant has written books for Apress and Simple-Talk. Grant presents at conferences and user groups, large and small, all over the world. He joined Redgate Software as a product evangelist in January 2011.</description>
      <twitter>@gfritchey</twitter>
      <linkedin>http://www.linkedin.com/in/scarydba</linkedin>
      <ContactURL>http://scarydba.com</ContactURL>
      <imageURL>https://api.twitter.com/1/users/profile_image?screen_name=@gfritchey</imageURL>
      <imageHeight>48</imageHeight>
      <imageWidth>48</imageWidth>
    </speaker>
    <speaker>
      <importID>13831</importID>
      <name>Edward Pollack</name>
      <label>
      </label>
      <description>Ed Pollack has over 20 years of experience in database and systems administration, which has developed his passion for performance optimization, database design, and making things go faster. He has spoken at many SQLSaturdays, 24 Hours of PASS, and PASS Summit. This led him to organize SQLSaturday Albany, which has become an annual event for New York’s Capital Region. Sharing these experiences with the community is a top priority, and encouraging everyone to take the leap into public speaking and engaging others, a passion.
In his free time, Ed enjoys video games, traveling, cooking exceptionally spicy foods, and hanging out with his amazing wife and sons.</description>
      <twitter>EdwardPollack</twitter>
      <linkedin>https://www.linkedin.com/profile/view?id=81593638</linkedin>
      <ContactURL>https://www.sqlshack.com/author/edward-pollack/</ContactURL>
      <imageURL>https://api.twitter.com/1/users/profile_image?screen_name=EdwardPollack</imageURL>
      <imageHeight>48</imageHeight>
      <imageWidth>48</imageWidth>
    </speaker>
    <speaker>
      <importID>8909</importID>
      <name>Aaron Bertrand</name>
      <label>
      </label>
      <description>Architect at Wayfair. Long-time MVP and bad habits attacker.</description>
      <twitter>AaronBertrand</twitter>
      <linkedin>
      </linkedin>
      <ContactURL>https://sqlblog.org</ContactURL>
      <imageURL>https://api.twitter.com/1/users/profile_image?screen_name=AaronBertrand</imageURL>
      <imageHeight>48</imageHeight>
      <imageWidth>48</imageWidth>
    </speaker>
    <speaker>
      <importID>25370</importID>
      <name>Steve Simon</name>
      <label>
      </label>
      <description>Steve Simon is a Database Solutions Architect with Business Knowledge Services Inc. He has been involved with database design and analysis for over 35 years. Steve has presented papers at numerous PASS Summits and PASS SQL Rallies. He is also regular presenter on the SQL Saturday circuit and he is a contributor on SQLShack.com</description>
      <twitter>SQLServerBoffin</twitter>
      <linkedin>http://www.linkedin.com/in/stephenrsimon/</linkedin>
      <ContactURL>http://www.sqlservercentral.com/blogs/simon_says/</ContactURL>
      <imageURL>https://api.twitter.com/1/users/profile_image?screen_name=SQLServerBoffin</imageURL>
      <imageHeight>48</imageHeight>
      <imageWidth>48</imageWidth>
    </speaker>
    <speaker>
      <importID>12378</importID>
      <name>David Bermingham</name>
      <label>
      </label>
      <description>David Bermingham is recognized within the community as a high availability expert and has been honored by his peers by being elected to be a MVP in Clustering since 2010 and most recently has been recognized as a Cloud and Datacenter MVP. David’s work as technical evangelist at SIOS has him focused on evangelizing Microsoft high availability and disaster recovery solutions for both on premise and cloud deployments. He lives in New Jersey with his wife and three kids where he a school board member, scout leader and musical director of an 8-piece jazz band, M-Town.</description>
      <twitter>https://twitter.com/daveberm</twitter>
      <linkedin>https://www.linkedin.com/profile/public-profile-settings?trk=prof-edit-edit-public_profile</linkedin>
      <ContactURL>http://clusteringformeremortals.com/</ContactURL>
      <imageURL>https://api.twitter.com/1/users/profile_image?screen_name=https://twitter.com/daveberm</imageURL>
      <imageHeight>48</imageHeight>
      <imageWidth>48</imageWidth>
    </speaker>
    <speaker>
      <importID>10526</importID>
      <name>Brian McCaig</name>
      <label>
      </label>
      <description>Brian McCaig has been working with SQL Server since it was introduced on OS2. He obtained certifications of MCSE, MCDBA and MCT while running his Microsoft Certified Training and Consulting business in the mid to late nineties. He then spent 11 years at Fidelity Investments managing their Centralized Enterprise SQL Server Service and is now at Eagle Investment Systems/Bank of NY Mellon managing their RD Infrastructure inclusive of all RDMS's.</description>
      <twitter>
      </twitter>
      <linkedin>
      </linkedin>
      <ContactURL>http://eagleinvsys.com</ContactURL>
      <imageURL>https://api.twitter.com/1/users/profile_image?screen_name=</imageURL>
      <imageHeight>48</imageHeight>
      <imageWidth>48</imageWidth>
    </speaker>
    <speaker>
      <importID>10672</importID>
      <name>Brandon Leach</name>
      <label>
      </label>
      <description>A Microsoft Data Platform MVP, Brandon manages the DB Operations team for financial company x. With a data estate of several petabytes, he puts a high focus on performance tuning and automation. He is a frequent speaker at events like conferences and user groups.</description>
      <twitter>SQLServerNerd</twitter>
      <linkedin>https://www.linkedin.com/in/sqlservernerd</linkedin>
      <ContactURL>
      </ContactURL>
      <imageURL>https://api.twitter.com/1/users/profile_image?screen_name=SQLServerNerd</imageURL>
      <imageHeight>48</imageHeight>
      <imageWidth>48</imageWidth>
    </speaker>
    <speaker>
      <importID>25874</importID>
      <name>Sunil Kadimdiwan</name>
      <label>
      </label>
      <description>Sunil Kadimdiwan Sunil Kadimdiwan has 25+ years’ experience in architecting and implementing database solutions. He has deep knowledge of the Microsoft SQL Server and Business Intelligence technology stack. He is a frequent speaker at SQL Saturdays, Code Camps, User Group meetings</description>
      <twitter>@skadimdiwan</twitter>
      <linkedin>https://www.linkedin.com/in/sunilkadimdiwan</linkedin>
      <ContactURL>http://www.infotrove.com/events.html</ContactURL>
      <imageURL>https://api.twitter.com/1/users/profile_image?screen_name=@skadimdiwan</imageURL>
      <imageHeight>48</imageHeight>
      <imageWidth>48</imageWidth>
    </speaker>
    <speaker>
      <importID>14520</importID>
      <name>George Walters</name>
      <label>
      </label>
      <description>Currently a partner technical strategist, George has been solving customer needs and issues. He can translate customer pain into potential solutions.

A seasoned Microsoft SQL and Azure expert, with over 20 years of experience with Microsoft SQL Server, Sybase, Oracle, and other relational databases.  

Specialties: Partner strategy, PreSales Engineering, Cloud Architecture, Enterprise Scalability, SQL Server performance, Business Intelligence, High Availability, Scale.
I volunteer and present relevant topics at SQL Saturday and internal Microsoft events</description>
      <twitter>https://twitter.com/geo_walters</twitter>
      <linkedin>https://www.linkedin.com/in/georgewalters</linkedin>
      <ContactURL>https://georgewalters.wordpress.com/</ContactURL>
      <imageURL>https://api.twitter.com/1/users/profile_image?screen_name=https://twitter.com/geo_walters</imageURL>
      <imageHeight>48</imageHeight>
      <imageWidth>48</imageWidth>
    </speaker>
    <speaker>
      <importID>18197</importID>
      <name>Kevin Kline</name>
      <label>
      </label>
      <description>Kevin Kline is a database and industry expert serving as Principal Program Manager at SentryOne, the industry leading SQL Server database tools vendor. A Microsoft SQL Server MVP since 2003, he is a founder and former president of PASS. Kevin is an author of many books, blogger, columnist, and popular international speaker. Kevin’s best known book is the best-selling SQL in a Nutshell and contributes monthly to Database Trends  Applications magazine. He tweets at @kekline and blogs at http://Blogs.SQLSentry.com/Author/KevinKline.</description>
      <twitter>kekline</twitter>
      <linkedin>http://www.linkedin.com/in/kekline/</linkedin>
      <ContactURL>http://blogs.sentryone.com/author/kevinkline</ContactURL>
      <imageURL>https://api.twitter.com/1/users/profile_image?screen_name=kekline</imageURL>
      <imageHeight>48</imageHeight>
      <imageWidth>48</imageWidth>
    </speaker>
    <speaker>
      <importID>20242</importID>
      <name>Michael Corey</name>
      <label>
      </label>
      <description>Michael Corey, Ntirety. Michael is experienced entrepreneur, Author and recognized expert on Relational Databases, Virtualization and Data Warehousing. Talkin’ Cloud identified Corey as one of top 200 cloud experts worth watching. VMware named Michael a vExpert and Oracle has named him an Oracle Ace. Michael has presented at conferences from Brazil to Australia.  Past President of IOUG, A founder of Professional Association of SQL Server. His newest book is from VMware Press on SQL Server.</description>
      <twitter>
      </twitter>
      <linkedin>
      </linkedin>
      <ContactURL>http://michaelcorey.ntirety.com/</ContactURL>
      <imageURL>https://api.twitter.com/1/users/profile_image?screen_name=</imageURL>
      <imageHeight>48</imageHeight>
      <imageWidth>48</imageWidth>
    </speaker>
    <speaker>
      <importID>20621</importID>
      <name>Mike Walsh</name>
      <label>
      </label>
      <description>Mike Walsh is an experienced SQL Server professional and has worked with SQL Server since version 6.5. He has been in the role of DBA, developer, and performance tuner, but always leans on his DBA and tuning experience. He has been awarded the SQL Server (now Data Platform) designation 6 times since 2011 and is a current MVP. He runs a SQL Server consultancy focused on DBA services and cloud enablement. He has spoken several times at PASS and regional events. In his spare time, he runs a small farm with his family in rural New Hampshire and is a call Firefighter in his small town.</description>
      <twitter>mike_walsh</twitter>
      <linkedin>http://www.linkedin.com/in/mikepwalsh</linkedin>
      <ContactURL>https://www.straightpathsql.com</ContactURL>
      <imageURL>https://api.twitter.com/1/users/profile_image?screen_name=mike_walsh</imageURL>
      <imageHeight>48</imageHeight>
      <imageWidth>48</imageWidth>
    </speaker>
    <speaker>
      <importID>11851</importID>
      <name>Jack Corbett</name>
      <label>
      </label>
      <description>JJack Corbett began working with SQL Server, Access, and VB in 1999, when he served an apprenticeship with a good friend who was the software development manager at the local paper mill. He found his niche and has concentrated on SQL Server development and administration since late 2000. He has worked with SQL Server through version 2017 and was a Microsoft Data Plaform MVP from October 2011 to October 2016. 

Jack is passionate about helping companies architect, design, and develop high performance applications based on the Microsoft Data Platform. He also has a passion for seeing database developers get the core application code (the database) protected under source control.

Jack has presented at many user groups and SQLSaturday even</description>
      <twitter>http://twitter.com/unclebiguns</twitter>
      <linkedin>http://www.linkedin.com/in/jackcorbett</linkedin>
      <ContactURL>http://www.wisemanorwiseguy.com</ContactURL>
      <imageURL>https://api.twitter.com/1/users/profile_image?screen_name=http://twitter.com/unclebiguns</imageURL>
      <imageHeight>48</imageHeight>
      <imageWidth>48</imageWidth>
    </speaker>
    <speaker>
      <importID>9242</importID>
      <name>Allan Hirt</name>
      <label>
      </label>
      <description>SQLHA, LLC founder, consultant, trainer, author, and business continuity, infrastructure, and virtualization expert Allan Hirt has been working with SQL Server since 1992 when it was still a Sybase product. He has also been clustering in Windows Server since the late 1990s when it was known as Wolfpack. Currently a dual Microsoft MVP (Data Platform; Cloud and Datacenter Management) as well as a VMware vExpert, Allan works with all sizes of customers, no matter if they are on premises or in the public cloud. He also delivers training and speaks at events over the world.</description>
      <twitter>SQLHA</twitter>
      <linkedin>https://www.linkedin.com/pub/allan-hirt/1/b72/673</linkedin>
      <ContactURL>http://www.sqlha.com/blog</ContactURL>
      <imageURL>https://api.twitter.com/1/users/profile_image?screen_name=SQLHA</imageURL>
      <imageHeight>48</imageHeight>
      <imageWidth>48</imageWidth>
    </speaker>
    <speaker>
      <importID>20540</importID>
      <name>Mike Hillwig</name>
      <label>
      </label>
      <description>Veteran DBA Mike Hillwig is a native Pittsburgher and resident of the Boston Suburbs. He’s a DBA Manager for a financial software company that’s owned by one of the world’s largest bank. Mike has been working with SQL Server since version 7 and has a background in infrastructure and network. Today, he manages a team of DBAs around the globe.</description>
      <twitter>@mikehillwig</twitter>
      <linkedin>http://www.linkedin.com/in/mikehillwig</linkedin>
      <ContactURL>http://www.mikehillwig.com</ContactURL>
      <imageURL>https://api.twitter.com/1/users/profile_image?screen_name=@mikehillwig</imageURL>
      <imageHeight>48</imageHeight>
      <imageWidth>48</imageWidth>
    </speaker>
    <speaker>
      <importID>16731</importID>
      <name>John Flannery</name>
      <label>
      </label>
      <description>John is the Data Architect at Evolution 1 in Simsbury Connecticut – and Adjunct Professor at Quinnipiac University in Hamden, Connecticut. He has 30 years industry experience; working with SQL server since version 4.2 on OS/2, Oracle since 7.3.4. John holds a Master of Science – Computer Science degree from Rensselaer (1995).  John is co-leader of the Hartford SQL User Group - and organizer of SQL Saturday 184.</description>
      <twitter>@AgileDataArch</twitter>
      <linkedin>http://www.linkedin.com/in/johnwflannery/</linkedin>
      <ContactURL>
      </ContactURL>
      <imageURL>https://api.twitter.com/1/users/profile_image?screen_name=@AgileDataArch</imageURL>
      <imageHeight>48</imageHeight>
      <imageWidth>48</imageWidth>
    </speaker>
    <speaker>
      <importID>26822</importID>
      <name>Timothy McAliley</name>
      <label>
      </label>
      <description>I am currently a Microsoft Cloud Solutions Architect in the Washington, DC area.  Previously, I was a Microsoft Technology Solutions Professional (TSP), a Microsoft Account Technology Strategist and a SQL Server Premier Field Engineer. Prior to Microsoft, I was a Technical Trainer and DBA in the Enterprise Security Group at Symantec . I have been in IT for over 20 years. My particular interests are IT operations, IT auditing, IT audit frameworks, IT service management (ITSM), ITIL, information security, project management, and database/application tier high availability solutions. I also co-run the Northern Virginia SQL Server User Group ( @novasl) and also co-run the Azure Datafest events.</description>
      <twitter>sysframeworks</twitter>
      <linkedin>https://www.linkedin.com/in/timothymcaliley/</linkedin>
      <ContactURL>
      </ContactURL>
      <imageURL>https://api.twitter.com/1/users/profile_image?screen_name=sysframeworks</imageURL>
      <imageHeight>48</imageHeight>
      <imageWidth>48</imageWidth>
    </speaker>
    <speaker>
      <importID>9364</importID>
      <name>Adam Machanic</name>
      <label>
      </label>
      <description>Adam Machanic is a Boston-based SQL Server developer, writer, and speaker. He focuses on large-scale data warehouse performance and development, and is the author of the award-winning SQL Server monitoring stored procedure, quot;sp_WhoIsActive.quot; He has contributed to several books on SQL Server, including quot;T-SQL Queryingquot; (Microsoft Press, 2015). He is a Microsoft Most Valuable Professional (MVP) for SQL Server.</description>
      <twitter>@AdamMachanic</twitter>
      <linkedin>https://www.linkedin.com/in/adammachanic</linkedin>
      <ContactURL>http://sqlblog.com/blogs/adam_machanic</ContactURL>
      <imageURL>https://api.twitter.com/1/users/profile_image?screen_name=@AdamMachanic</imageURL>
      <imageHeight>48</imageHeight>
      <imageWidth>48</imageWidth>
    </speaker>
  </speakers>
  <events>
    <event>
      <importID>10070</importID>
      <speakers>
        <speaker>
          <id>10070</id>
          <name>Ayad Shammout</name>
        </speaker>
      </speakers>
      <track>Constitution</track>
      <location>
        <name>N/A</name>
      </location>
      <title>Building BI Semantic Model Tabular in 60 minutes</title>
      <description>SQL Server 2012 introduces the new Analysis Services Tabular Mode. BI Semantic Model (BISM) Tabular is in-memory database in Analysis Services using state-of-the-art compression algorithms. BI Semantic Models can be developed in either Visual Studio or in Excel using the SQL Server 2012 PowerPivot add-in. In this session, I will show you how to build a complete solution in Tabular and creating one from the ground up, deploy a rich semantic model and discover a simpler method for analyzing business data. You also learn the basics of DAX language and how to manage role based security and partitioning in a Tabular model. You will be able to create your BISM Tabular models, and gain a solid background to enable you starting your next project.</description>
      <startTime>3/29/2014 12:00:00 AM</startTime>
      <endTime>3/29/2014 1:00:00 AM</endTime>
    </event>
    <event>
      <importID>9364</importID>
      <speakers>
        <speaker>
          <id>9364</id>
          <name>Adam Machanic</name>
        </speaker>
      </speakers>
      <track>Longfellow</track>
      <location>
        <name>N/A</name>
      </location>
      <title>Query Tuning Mastery: Clash of the Row Goals</title>
      <description>The fight for better performance is a battle of wits: your mind, your intelligence, and your honor pitted against the less-than-dependable whims of the Query Optimizer. But alas, the arbitrary rewrites and clunky hints leveraged by most developers to get around optimization deficiencies make things feel less like a proper duel and more like a skirmish at the sandbox. To truly engage your enemy you must comprehend his inner workings, and in the case of the Query Optimizer, that means you must delve into the mysteries of "row goals." These internal metrics are tracked and enforced within Top iterators--and they exhibit a considerable amount of influence over plan shape and flow, both at compile time and as your query runs. Attend this session to learn how to take charge of optimization, expertly mold your query plans, and gain a new set of tools for eliminating bottlenecks in even your most complex problem queries. En garde!</description>
      <startTime>3/29/2014 12:00:00 AM</startTime>
      <endTime>3/29/2014 1:00:00 AM</endTime>
    </event>
    <event>
      <importID>10591</importID>
      <speakers>
        <speaker>
          <id>10591</id>
          <name>Bob Pusateri</name>
        </speaker>
      </speakers>
      <track>Longfellow</track>
      <location>
        <name>N/A</name>
      </location>
      <title>Whatcha Doin'? Passive Security for Hostile Environments</title>
      <description>Ideal database security settings usually exist in books, but rarely in reality. Is your CIO a member of the sysadmin role because they demanded it? Or maybe some users have rights for purely political reasons? Just because you can't enforce security through typical means doesn't mean you're powerless. Attend this session to learn about the features SQL Server provides that will allow you to keep track of what your users are up to at all times and sleep a little easier. Through various scenarios and demos, see how technologies such as event notifications, auditing, and extended events can help ensure nothing happens on your system without you knowing about it. Even in optimally secured environments these techniques can still come in handy. The best security is often that which cannot be seen.</description>
      <startTime>3/29/2014 12:00:00 AM</startTime>
      <endTime>3/29/2014 1:00:00 AM</endTime>
    </event>
    <event>
      <importID>11024</importID>
      <speakers>
        <speaker>
          <id>11024</id>
          <name>Bryan Cafferky</name>
        </speaker>
      </speakers>
      <track>Constitution</track>
      <location>
        <name>N/A</name>
      </location>
      <title>So you think you know SSIS? What about Scripting? </title>
      <description>If you don’t know how to extend the power of SSIS through the Script Task and Script Component, you don’t know SSIS.  Empower your SSIS skills by learning how to add  .Net scripts to your packages using C# or VB.Net code to access the full power of Windows and its object models.  In this presentation Bryan will walk through the basics of SSIS scripting building to more complex examples using real world cases.  Learn how to load any external flat file by taking direct control, how to leverage the power of the SQL Server Object Model (SMO), ActiveX Data Objects (ADO.Net), and use the power of Regular Expressions for advanced string parsing.  You will leave with the basics you need to start scripting and a number of useful scripts you can add to your packages.</description>
      <startTime>3/29/2014 12:00:00 AM</startTime>
      <endTime>3/29/2014 1:00:00 AM</endTime>
    </event>
    <event>
      <importID>14731</importID>
      <speakers>
        <speaker>
          <id>14731</id>
          <name>Grant Fritchey</name>
        </speaker>
      </speakers>
      <track>Hawthorne</track>
      <location>
        <name>N/A</name>
      </location>
      <title>Statistics and Query Optimization</title>
      <description>There are any number of tricks and traps around getting the query optimizer to provide you with an optimal execution plan that gets you your data quickly and efficiently. But, at the end of the day, the principal driving factor of the optimizer, and therefore of your queries, are the statistics that define your data. This session teaches you how those statistics are put together and maintained by SQL Server. Different types of maintenance results in different levels of accuracy within statistics so we detail what the structures and information looks like after this maintenance. Your understanding of how the optimizer works with statistics will better enable you to understand why you’re getting the performance and types of execution plans that you are getting. Understanding enables you to write better t-sql statements and deal with performance problems such as bad parameter sniffing.</description>
      <startTime>3/29/2014 12:00:00 AM</startTime>
      <endTime>3/29/2014 1:00:00 AM</endTime>
    </event>
    <event>
      <importID>10672</importID>
      <speakers>
        <speaker>
          <id>10672</id>
          <name>Brandon Leach</name>
        </speaker>
      </speakers>
      <track>Constitution</track>
      <location>
        <name>N/A</name>
      </location>
      <title>Implementing a HIPAA Compliance Strategy with SQL Server</title>
      <description>HIPAA puts a lot of responsibility on our companies and compliance can be hard to maintain. Today medical data is more valuable on the black market than a social security number or a credit card.  As DBAs we're charged with the security of our data and thus act as front line defense.

In this hour long session We'll delve into the Health Insurance Portability and Accountability Act (HIPAA) and what implications it has for us as data professionals. We'll discuss SQL Server best practices that can help protect ourselves, our company, and the people whom we serve. We'll also dive into features in SQL Server that can help in this endeavor. </description>
      <startTime>3/29/2014 12:00:00 AM</startTime>
      <endTime>3/29/2014 1:00:00 AM</endTime>
    </event>
    <event>
      <importID>18197</importID>
      <speakers>
        <speaker>
          <id>18197</id>
          <name>Kevin Kline</name>
        </speaker>
      </speakers>
      <track>Hawthorne</track>
      <location>
        <name>N/A</name>
      </location>
      <title>SQL Server Internals and Architecture</title>
      <description>Let’s face it.  You can effectively do many IT jobs related to SQL Server without knowing the internals of how SQL Server works.  Many great developers, DBAs, and designers get their day-to-day work completed on time and with reasonable quality while never really knowing what’s happening behind the scenes.  But if you want to take your skills to the next level, it’s critical to know SQL Server’s internal processes and architecture.  This session will answer questions like:
-       What’s different about 32- and 64-bit systems?
-       What are the various areas of memory inside of SQL Server?
-       How are queries handled behind the scenes?
-       What does SQL Server do with procedural code, like functions, procedures, and triggers?
-       What happens during checkpoints?  Lazywrites?
-       How are IOs handled with regards to transaction logs and database?
-       What happens when transaction logs and databases grow or shrinks?
</description>
      <startTime>3/29/2014 12:00:00 AM</startTime>
      <endTime>3/29/2014 1:00:00 AM</endTime>
    </event>
    <event>
      <importID>11025</importID>
      <speakers>
        <speaker>
          <id>11025</id>
          <name>Bryan Cafferky</name>
        </speaker>
      </speakers>
      <track>Concord</track>
      <location>
        <name>N/A</name>
      </location>
      <title>Dimensional Modeling:  The Heart of the Data Warehouse</title>
      <description>In this presentation, Bryan will explain the principles of Dimensional Modeling, the foundation of a data warehouse.  He will identify best practices and pitfalls to avoid especially if you come from a relational database background.  The focus is to show how dimensional modeling is applied and provide you with the skills to build your own dimensional models.  </description>
      <startTime>3/29/2014 12:00:00 AM</startTime>
      <endTime>3/29/2014 1:00:00 AM</endTime>
    </event>
    <event>
      <importID>26710</importID>
      <speakers>
        <speaker>
          <id>26710</id>
          <name>Tim Radney</name>
        </speaker>
      </speakers>
      <track>Bunker Hill</track>
      <location>
        <name>N/A</name>
      </location>
      <title>You Inherited a Database, Now What?</title>
      <description>You have recently inherited the support of a new or existing database, what are the things you should immediately check and start monitoring and what are the things that you should address over the next few weeks. When taking over support of a database or system, you cannot ASSUME anything. At the end of this session you will have a nice checklist of things you should check and be doing on ALL your databases not just the one you inherited. Whether you are a seasoned DBA or just starting out, this session should be informative and something you can relate to. </description>
      <startTime>3/29/2014 12:00:00 AM</startTime>
      <endTime>3/29/2014 1:00:00 AM</endTime>
    </event>
    <event>
      <importID>16205</importID>
      <speakers>
        <speaker>
          <id>16205</id>
          <name>Joseph D'Antoni</name>
        </speaker>
      </speakers>
      <track>Concord</track>
      <location>
        <name>N/A</name>
      </location>
      <title>In-Memory Columnstore Indexes--Make Your Data Warehouse Fly </title>
      <description>Columnstore indexes were introduced in SQL Server 2012, along with a new type of query processing "batch mode". In SQL 2014 they get even better--we can use a Columnstore index as a clustered index and update it. In this session we will explore the basics and beyond of Columnstore indexes and how they can help your warehouse performance. </description>
      <startTime>3/29/2014 12:00:00 AM</startTime>
      <endTime>3/29/2014 1:00:00 AM</endTime>
    </event>
    <event>
      <importID>13832</importID>
      <speakers>
        <speaker>
          <id>13832</id>
          <name>Edward Pollack</name>
        </speaker>
      </speakers>
      <track>Thoreau</track>
      <location>
        <name>N/A</name>
      </location>
      <title>Diving Into Query Execution Plans</title>
      <description>There is no better way to understand how TSQL is executing than through the execution plan.  We will go into detail about the more complex parts of execution plans, relating them to other query statistics, and use this information to improve overall query performanc.  Be sure to bring your safety helmet!</description>
      <startTime>3/29/2014 12:00:00 AM</startTime>
      <endTime>3/29/2014 1:00:00 AM</endTime>
    </event>
    <event>
      <importID>26822</importID>
      <speakers>
        <speaker>
          <id>26822</id>
          <name>Timothy McAliley</name>
        </speaker>
      </speakers>
      <track>Constitution</track>
      <location>
        <name>N/A</name>
      </location>
      <title>Floating on a Hybrid Cloud: SQL Server 2014  Windows Azure </title>
      <description>In this session we will discuss and demonstrate the cloud integration capabilities of SQL Server 2014, the Windows Azure Platform, and scenarios for leveraging hybrid cloud infrastructure. We will discuss and demonstrate deploying SQL Server 2014 running on a Windows Azure Virtual Machine and also discuss and demonstrate the Windows Azure SQL Database.  We will also discuss best practices and demonstrate techniques for managing both on-premises and cloud-based resources.</description>
      <startTime>3/29/2014 12:00:00 AM</startTime>
      <endTime>3/29/2014 1:00:00 AM</endTime>
    </event>
    <event>
      <importID>10526</importID>
      <speakers>
        <speaker>
          <id>10526</id>
          <name>Brian McCaig</name>
        </speaker>
      </speakers>
      <track>Lexington</track>
      <location>
        <name>N/A</name>
      </location>
      <title>SQL Server cell level and transparent data encryption a case study</title>
      <description>The session will cover a practical implementation of the use of cell level encryption combined with the protection of transparent data encryption.
Agenda:
Encryption Options for SQL Server. For this session, SQL Server 2008 R2 will be the reference Model.
What is Cell Level Encryption
What is Transparent Data Encryption
Can they be deployed together
The session will include a practical implementation example.
A demo will be threaded into the presentation to provide clarity and understanding of the code required for implementation.
Technical Level: 200</description>
      <startTime>3/29/2014 12:00:00 AM</startTime>
      <endTime>3/29/2014 1:00:00 AM</endTime>
    </event>
    <event>
      <importID>13831</importID>
      <speakers>
        <speaker>
          <id>13831</id>
          <name>Edward Pollack</name>
        </speaker>
      </speakers>
      <track>Concord</track>
      <location>
        <name>N/A</name>
      </location>
      <title>Dynamic SQL: Writing Efficient Queries on the Fly</title>
      <description>Dynamic SQL can be a powerful tool that allows you to write fast  efficient queries when the specifics may not be known until run-time.  It can also be complex, difficult to read and debug, and the source of some of the most confusing TSQL you'll ever see.

Explore the many uses for dynamic SQL as well as best practices for writing, testing, debugging, and maintaining it, with the bonus of helping to improve the sanity of your coworkers (and your own) in the process!</description>
      <startTime>3/29/2014 12:00:00 AM</startTime>
      <endTime>3/29/2014 1:00:00 AM</endTime>
    </event>
    <event>
      <importID>23794</importID>
      <speakers>
        <speaker>
          <id>23794</id>
          <name>Mohammad Yusuf</name>
        </speaker>
      </speakers>
      <track>Longfellow</track>
      <location>
        <name>N/A</name>
      </location>
      <title>An Introduction to Database Design And Management</title>
      <description>Introduces students to basic concepts used in database design. Student is first introduce to what is a database and gradually introduces students to more advanced topics that include creating a database, tables, constraints and relationships, normalization, Structured Query Language (DML, DDL, DCL), data modeling, design and implementation.*** This is a full semester course condensed into 4 hours. ****</description>
      <startTime>3/29/2014 12:00:00 AM</startTime>
      <endTime>3/29/2014 1:00:00 AM</endTime>
    </event>
    <event>
      <importID>26709</importID>
      <speakers>
        <speaker>
          <id>26709</id>
          <name>Tim Radney</name>
        </speaker>
      </speakers>
      <track>Bunker Hill</track>
      <location>
        <name>N/A</name>
      </location>
      <title>Know Backups and Know Recovery</title>
      <description>It is easy to schedule full backups to run each night, but is that the right decision for your organization?  You say you have a backup strategy, but what is your recovery strategy?  Do you have a well-executed recovery plan?  In this session I will cover several methods for performing much needed backups and how to recover those backups.  Full, Differential, File Group, Transaction logs and recovery the tail end of a the log.  He will discuss industry best practices and hopefully cause you to validate and test your current strategy.</description>
      <startTime>3/29/2014 12:00:00 AM</startTime>
      <endTime>3/29/2014 1:00:00 AM</endTime>
    </event>
    <event>
      <importID>21643</importID>
      <speakers>
        <speaker>
          <id>21643</id>
          <name>Paresh Motiwala</name>
        </speaker>
      </speakers>
      <track>Hawthorne</track>
      <location>
        <name>N/A</name>
      </location>
      <title>Database Forensics - Part 1</title>
      <description>These are the days of increasing cyber and computer crimes. 
As DBAs and guardians of corporate data, it is your paramount duty to not only prevent any data loss but also discover lost , damaged or sabotaged data.
But how can you do that without destroying evidence? Remember electronic evidence is extremely fragile.
In this the first of the two part session, we will explore the following:
1. Fundamentals of Computer Forensics
2. Tools to use in Computer Forensics--Data Acquisition
3. Processing a crime scene
4. Network Forensics and Live Acquistions.
5. Submitting reports

</description>
      <startTime>3/29/2014 12:00:00 AM</startTime>
      <endTime>3/29/2014 1:00:00 AM</endTime>
    </event>
    <event>
      <importID>8909</importID>
      <speakers>
        <speaker>
          <id>8909</id>
          <name>Aaron Bertrand</name>
        </speaker>
      </speakers>
      <track>Hawthorne</track>
      <location>
        <name>N/A</name>
      </location>
      <title>T-SQL : Bad Habits  Best Practices</title>
      <description>Bad habits: we all have them. SELECT * is the obvious one; but in this session you will learn about various other habits and why they can be bad for performance or maintainability. You will also learn about best practices that will help you avoid falling into some of these bad habits. Come learn how these habits develop, what kind of problems they can lead to, and how you can avoid them - leading to more efficient code, a more productive work environment, and - in a lot of cases – both.</description>
      <startTime>3/29/2014 12:00:00 AM</startTime>
      <endTime>3/29/2014 1:00:00 AM</endTime>
    </event>
    <event>
      <importID>25370</importID>
      <speakers>
        <speaker>
          <id>25370</id>
          <name>Steve Simon</name>
        </speaker>
      </speakers>
      <track>Bunker Hill</track>
      <location>
        <name>N/A</name>
      </location>
      <title>Mind your language!!   Cursors are a dirty word</title>
      <description>Although many SQL Server folks become irate at the thought of using cursors, like anything else in life there is a time and place.
In this hands-on presentation, we shall be looking at practical cases where the utilization of a cursor can prove to be the most efficient and effective solution and THIS is based upon actual execution plans.
</description>
      <startTime>3/29/2014 12:00:00 AM</startTime>
      <endTime>3/29/2014 1:00:00 AM</endTime>
    </event>
    <event>
      <importID>9242</importID>
      <speakers>
        <speaker>
          <id>9242</id>
          <name>Allan Hirt</name>
        </speaker>
      </speakers>
      <track>Thoreau</track>
      <location>
        <name>N/A</name>
      </location>
      <title>Patch Management Strategies for SQL Server</title>
      <description>We all have to deal with applying some sort of update to Windows, SQL Server, and/or hardware. Keeping things up to date is crucial for supportability, not to mention other things like security, performance, and stability. Since patching often involves downtime, you need to be careful not only what you apply to avoid problems, but also find ways to minimize the impact to the business and end users. This session will cover topics such as how to approach patching including what changes you should and should not consume, features that may help you automate or script patching, and developing your own long term patch management strategy.</description>
      <startTime>3/29/2014 12:00:00 AM</startTime>
      <endTime>3/29/2014 1:00:00 AM</endTime>
    </event>
    <event>
      <importID>11851</importID>
      <speakers>
        <speaker>
          <id>11851</id>
          <name>Jack Corbett</name>
        </speaker>
      </speakers>
      <track>Concord</track>
      <location>
        <name>N/A</name>
      </location>
      <title>Inroduction to Triggers</title>
      <description>This session will give a brief overview of the different types of triggers available in SQL Server (DDL  DML) and then go into more detail on how and when to use DML triggers. This session will cover misconceptions about how triggers work, when triggers should and shouldn't be used (we will discuss options), common mistakes, and how to fix the most common mistakes. After attending this session a person will: 1. Identify different types of triggers and when to use them. 2. Be able to identify when a trigger is the right solution 3. Be able to write triggers that perform well </description>
      <startTime>3/29/2014 12:00:00 AM</startTime>
      <endTime>3/29/2014 1:00:00 AM</endTime>
    </event>
    <event>
      <importID>11258</importID>
      <speakers>
        <speaker>
          <id>11258</id>
          <name>Chris Bell</name>
        </speaker>
      </speakers>
      <track>Thoreau</track>
      <location>
        <name>N/A</name>
      </location>
      <title>Optimizing Protected Indexes</title>
      <description>As a SQL Server DBA I see my role having 2 main focuses. First is to protect the data and second is to ensure performance is maximized. More often than not companies forget about data security when they focus on performance tuning. In this presentation I will mention a few cases where encryption could have saved a lot of hassle. I will then demo a method that can be used to "index" commonly searched on encrypted values (ex: SSNs, Credit Card, etc) helping reduce the impact on the performance of a query.</description>
      <startTime>3/29/2014 12:00:00 AM</startTime>
      <endTime>3/29/2014 1:00:00 AM</endTime>
    </event>
    <event>
      <importID>27546</importID>
      <speakers>
        <speaker>
          <id>27546</id>
          <name>Varsham Papikian</name>
        </speaker>
      </speakers>
      <track>Constitution</track>
      <location>
        <name>N/A</name>
      </location>
      <title>Yes, you can do it in SSMS: tips and tricks.</title>
      <description>SQL Server Management Studio (SSMS) is probably the most frequently used tool by SQL Server Professionals. Yet it has many features or 'extra flexibility' that some people are not aware of. This session is going to be a fully demo-driven, practical demonstration of many such features. The tips will help you to become more productive at work.
</description>
      <startTime>3/29/2014 12:00:00 AM</startTime>
      <endTime>3/29/2014 1:00:00 AM</endTime>
    </event>
    <event>
      <importID>17044</importID>
      <speakers>
        <speaker>
          <id>17044</id>
          <name>John Miner</name>
        </speaker>
      </speakers>
      <track>Lexington</track>
      <location>
        <name>N/A</name>
      </location>
      <title>Effective use of temporary tables</title>
      <description>Every developer eventually comes against business logic that can’t be handled with a single simple or complex query. TSQL provides the developer with several constructs that can store temporary result sets that are passed to the next query in the script.

I will be covering these various TSQL techniques with examples using the [AdventureWorks] database as well as a toy database called AUTOS. The pros and cons of each construct will be examined. Advanced options like enabling trace flag 1118 will be explored.

Coverage:

1 – Derived tables.
2 – Local temporary tables.
3 – Global temporary tables.
4 – Table variables.
5 – Common Table Expressions (CTE).
6 – User databases in [tempdb].
7 – Trace Flag 1118.
</description>
      <startTime>3/29/2014 12:00:00 AM</startTime>
      <endTime>3/29/2014 1:00:00 AM</endTime>
    </event>
    <event>
      <importID>12378</importID>
      <speakers>
        <speaker>
          <id>12378</id>
          <name>David Bermingham</name>
        </speaker>
      </speakers>
      <track>Concord</track>
      <location>
        <name>N/A</name>
      </location>
      <title>High Availability with Windows Server 2012 R2 and SQL Server 2014</title>
      <description>This lecture (20% slides, 80% demonstrations) takes a close look at the new features of Windows Server 2012 R2 clustering and how it affects your SQL Server availability.  In addition, the new availability features of SQL Server 2014 will be reviewed.  This session is geared for those new to Windows Server clustering and SQL Server AlwaysOn but will also be beneficial to those with experience looking to learn about the new high availability features in both Windows Server 2012 R2 and SQL Server 2014. </description>
      <startTime>3/29/2014 12:00:00 AM</startTime>
      <endTime>3/29/2014 1:00:00 AM</endTime>
    </event>
    <event>
      <importID>10670</importID>
      <speakers>
        <speaker>
          <id>10670</id>
          <name>Brandon Leach</name>
        </speaker>
      </speakers>
      <track>Lexington</track>
      <location>
        <name>N/A</name>
      </location>
      <title>Treating Tables Like Legos, Partitioning Basics</title>
      <description>Partitioning allows us to isolate parts of our table as small chunks called partitions.  In turn, these partitions allow us to do some really cool tricks for manageability and performance.  In this session we'll look at the concepts surrounding partitioning and how we can apply them.  We'll reinforce what we cover with some cool demo's showing some really neat tricks.</description>
      <startTime>3/29/2014 12:00:00 AM</startTime>
      <endTime>3/29/2014 1:00:00 AM</endTime>
    </event>
    <event>
      <importID>20540</importID>
      <speakers>
        <speaker>
          <id>20540</id>
          <name>Mike Hillwig</name>
        </speaker>
      </speakers>
      <track>Lexington</track>
      <location>
        <name>N/A</name>
      </location>
      <title>Recovery and Backup for Beginners</title>
      <description>We all know that backups are important. But are we building a backup strategy that can recover in a manner that meets business needs? All too often, we plan a backup strategy without a recovery strategy.

In this session, veteran DBA Mike Hillwig will start with understanding the recovery strategy and work toward implementing the right backups to meet that recovery strategy.  He'll also set the record straight around some very common myths around database recovery and backups. </description>
      <startTime>3/29/2014 12:00:00 AM</startTime>
      <endTime>3/29/2014 1:00:00 AM</endTime>
    </event>
    <event>
      <importID>20242</importID>
      <speakers>
        <speaker>
          <id>20242</id>
          <name>Michael Corey</name>
        </speaker>
      </speakers>
      <track>Thoreau</track>
      <location>
        <name>N/A</name>
      </location>
      <title>Virtualizing SQL Server: Doing It Right – The SeQueL</title>
      <description>A database is a very resource intensive by its very nature and one of the most resource intensive applications you will ever virtualize. If best practices are not followed, the database will never perform as needed. This presentation will teach the DBA best practices for Virtualizing SQL Server databases with a heavy emphasis on VMware. Topics include Design, Storage, Processor, and Memory  Network considerations. This presentation is based upon the very popular presentation given at VMworld in San Francisco and Barcelona. </description>
      <startTime>3/29/2014 12:00:00 AM</startTime>
      <endTime>3/29/2014 1:00:00 AM</endTime>
    </event>
    <event>
      <importID>10149</importID>
      <speakers>
        <speaker>
          <id>10149</id>
          <name>Bradley Ball</name>
        </speaker>
      </speakers>
      <track>Bunker Hill</track>
      <location>
        <name>N/A</name>
      </location>
      <title>Trimming Indexes Getting Your Database In Shape</title>
      <description>Indexes are a wonderful thing.  We should be using them, and we should be maintaining them.  But over time our production databases start to look a little pudgy around the mid-section.  Maybe they are a little bloated with Unused Indexes, maybe they have Duplicate Indexes, and possibly even Reverse Indexes.  The first step to fixing these problems it so see if you have them, and if you do the second is to set about fixing them. You could be costing yourself CPU cycles, I/Op’s, and space and never even know it.</description>
      <startTime>3/29/2014 12:00:00 AM</startTime>
      <endTime>3/29/2014 1:00:00 AM</endTime>
    </event>
    <event>
      <importID>20621</importID>
      <speakers>
        <speaker>
          <id>20621</id>
          <name>Mike Walsh</name>
        </speaker>
      </speakers>
      <track>Thoreau</track>
      <location>
        <name>N/A</name>
      </location>
      <title>What I Wish I Knew Before Becoming a DBA</title>
      <description>Are you interested in becoming a DBA? Would you consider yourself an accidental DBA?

In this talk, Mike Walsh will share some thoughts on the role of DBA - How to become one, What a DBA's priorities should be and what the pros and cons of being one are.

He'll look through his 13 years of DBA experience and share some of the lessons he wish he learned before he started out. </description>
      <startTime>3/29/2014 12:00:00 AM</startTime>
      <endTime>3/29/2014 1:00:00 AM</endTime>
    </event>
    <event>
      <importID>25874</importID>
      <speakers>
        <speaker>
          <id>25874</id>
          <name>Sunil Kadimdiwan</name>
        </speaker>
      </speakers>
      <track>Bunker Hill</track>
      <location>
        <name>N/A</name>
      </location>
      <title>Develop Impressive Dashboards using SSRS 2012</title>
      <description>Microsoft Reporting Services 2012 has many exciting features. You can show your business data on Maps, Charts including Sparklines, Data bars and Indicators. Make them interactive, so that your users can drilldown to details. In this session I will show you how can make use of these and other enhancements in SSRS 2012.</description>
      <startTime>3/29/2014 12:00:00 AM</startTime>
      <endTime>3/29/2014 1:00:00 AM</endTime>
    </event>
    <event>
      <importID>16731</importID>
      <speakers>
        <speaker>
          <id>16731</id>
          <name>John Flannery</name>
        </speaker>
      </speakers>
      <track>Lexington</track>
      <location>
        <name>N/A</name>
      </location>
      <title>What the Hekaton</title>
      <description>In SQL Server 2014 – Microsoft is introducing In-Memory OLTP.  (Formally known as project Hekaton.)  In this session – we will introduce this technology, optimize an existing AdventureWorks stored procedure to use In-Memory OLTP, and discuss other applications such as ETL.</description>
      <startTime>3/29/2014 12:00:00 AM</startTime>
      <endTime>3/29/2014 1:00:00 AM</endTime>
    </event>
    <event>
      <importID>24658</importID>
      <speakers>
        <speaker>
          <id>24658</id>
          <name>Stacia Varga</name>
        </speaker>
      </speakers>
      <track>Hawthorne</track>
      <location>
        <name>N/A</name>
      </location>
      <title>(Way Too Much) Fun with Reporting Services </title>
      <description>Head starting to explode from all the technical information you’re absorbing?  Come spend a session with us while we play games with Reporting Services…literally!  Come watch as Stacia Misner and a special guest introduce you to some  word play, all wrapped up in SQL Server Reporting Services.  She'll push the limits with what can be built in SSRS and show you how to have fun while doing it.  Board games and SQL…who could ask for more?</description>
      <startTime>3/29/2014 12:00:00 AM</startTime>
      <endTime>3/29/2014 1:00:00 AM</endTime>
    </event>
    <event>
      <importID>9511</importID>
      <speakers>
        <speaker>
          <id>9511</id>
          <name>Andy Leonard</name>
        </speaker>
      </speakers>
      <track>Longfellow</track>
      <location>
        <name>N/A</name>
      </location>
      <title>Designing an SSIS Framework </title>
      <description>In this “demo-tastic” presentation, SSIS trainer, author, and consultant Andy Leonard explains the what, why, and how of an SSIS framework that delivers metadata-driven package execution, connections management, and centralizes logging. Key takeaways: 1) Developers can migrate packages from Development, through their lifecycle, to Production without editing SSIS Connection Managers properties. 2) A metadata-driven approach to SSIS package execution. 3) Demonstration of a centralized logging reporting application.</description>
      <startTime>3/29/2014 12:00:00 AM</startTime>
      <endTime>3/29/2014 1:00:00 AM</endTime>
    </event>
    <event>
      <importID>14520</importID>
      <speakers>
        <speaker>
          <id>14520</id>
          <name>George Walters</name>
        </speaker>
      </speakers>
      <track>Longfellow</track>
      <location>
        <name>N/A</name>
      </location>
      <title>SQL Server 2012 AlwaysOn Availability Groups</title>
      <description>The AlwaysOn Availability Groups feature is a high-availability and disaster-recovery solution that provides an enterprise-level alternative to database mirroring.</description>
      <startTime>3/29/2014 12:00:00 AM</startTime>
      <endTime>3/29/2014 1:00:00 AM</endTime>
    </event>
  </events>
</GuidebookXML>